caped_ai_metrics/ScoreKeeper.py
caped_ai_metrics/__init__.py
caped_ai_metrics/_version.py
caped_ai_metrics-1.2.5.dist-info/licenses/LICENSE.txt
caped_ai_metrics-1.2.5.dist-info/METADATA
caped_ai_metrics-1.2.5.dist-info/WHEEL
caped_ai_metrics-1.2.5.dist-info/top_level.txt
caped_ai_metrics-1.2.5.dist-info/RECORD
