Metadata-Version: 2.4
Name: caped-ai-metrics
Version: 1.2.5
Summary: Metric computation toolkit for segmentation and classification tasks
Author: Varun Kapoor
Author-email: randomaccessiblekapoor@gmail.com
Classifier: Development Status :: 3 - Alpha
Classifier: Natural Language :: English
Classifier: License :: OSI Approved :: MIT License
Classifier: Operating System :: OS Independent
Classifier: Programming Language :: Python
Classifier: Programming Language :: Python :: 3.9
License-File: LICENSE.txt
Dynamic: author
Dynamic: author-email
Dynamic: classifier
Dynamic: description
Dynamic: description-content-type
Dynamic: license-file
Dynamic: summary
